rtcvis/__init__.py
rtcvis/conv.py
rtcvis/exceptions.py
rtcvis/line.py
rtcvis/plf.py
rtcvis/plot_conv.py
rtcvis/plot_plf.py
rtcvis/point.py
rtcvis/py.typed
rtcvis-0.3.0.dist-info/licenses/LICENSE
rtcvis-0.3.0.dist-info/METADATA
rtcvis-0.3.0.dist-info/WHEEL
rtcvis-0.3.0.dist-info/top_level.txt
rtcvis-0.3.0.dist-info/RECORD
