Metadata-Version: 2.4
Name: rtcvis
Version: 0.3.0
Summary: Tool for visualizing Real Time Calculus (RTC) operations
License: MIT License
Project-URL: Repository, https://github.com/epkRichi/rtcvis
Keywords: math,visualization,education
Classifier: Programming Language :: Python :: 3
Classifier: Operating System :: OS Independent
Requires-Python: >=3.10
License-File: LICENSE
Provides-Extra: plot
Requires-Dist: matplotlib; extra == "plot"
Requires-Dist: PyQt6; extra == "plot"
Provides-Extra: dev
Requires-Dist: pytest; extra == "dev"
Requires-Dist: pre-commit; extra == "dev"
Requires-Dist: mypy; extra == "dev"
Requires-Dist: black; extra == "dev"
Requires-Dist: build; extra == "dev"
Requires-Dist: flake8; extra == "dev"
Dynamic: license-file
